osm_ai_helper/__init__.py
osm_ai_helper/convert_to_vlm_dataset.py
osm_ai_helper/convert_to_yolo_dataset.py
osm_ai_helper/download_osm.py
osm_ai_helper/export_osm.py
osm_ai_helper/group_elements_and_download_tiles.py
osm_ai_helper/run_inference.py
osm_ai_helper/utils/__init__.py
osm_ai_helper/utils/coordinates.py
osm_ai_helper/utils/inference.py
osm_ai_helper/utils/osm.py
osm_ai_helper/utils/plots.py
osm_ai_helper/utils/polygons.py
osm_ai_helper/utils/tiles.py
osm_ai_helper-1.5.3.dist-info/licenses/LICENSE
osm_ai_helper-1.5.3.dist-info/METADATA
osm_ai_helper-1.5.3.dist-info/WHEEL
osm_ai_helper-1.5.3.dist-info/top_level.txt
osm_ai_helper-1.5.3.dist-info/RECORD
