Metadata-Version: 2.4
Name: osm-ai-helper
Version: 1.5.3
License: Apache-2.0
Project-URL: Documentation, https://mozilla-ai.github.io/osm-ai-helper/
Project-URL: Issues, https://github.com/mozilla-ai/osm-ai-helper/issues
Project-URL: Source, https://github.com/mozilla-ai/osm-ai-helper
Requires-Python: >=3.10
License-File: LICENSE
Requires-Dist: fire
Requires-Dist: huggingface_hub
Requires-Dist: loguru
Requires-Dist: requests
Requires-Dist: requests_oauthlib
Requires-Dist: sam2
Requires-Dist: setuptools==75.8.2
Requires-Dist: scikit-image
Requires-Dist: shapely
Requires-Dist: ultralytics
Provides-Extra: demo
Requires-Dist: folium; extra == "demo"
Requires-Dist: streamlit; extra == "demo"
Requires-Dist: streamlit-folium; extra == "demo"
Provides-Extra: docs
Requires-Dist: mkdocs; extra == "docs"
Requires-Dist: mkdocs-material; extra == "docs"
Requires-Dist: mkdocstrings-python; extra == "docs"
Provides-Extra: tests
Requires-Dist: pytest<9,>=8; extra == "tests"
Requires-Dist: pytest-sugar>=0.9.6; extra == "tests"
Dynamic: license-file
